xPlotUtil/PlotWindow.py
xPlotUtil/__init__.py
xPlotUtil/Source/AlgebraicExpressions.py
xPlotUtil/Source/DockedOptions.py
xPlotUtil/Source/GaussianFit.py
xPlotUtil/Source/LorentzianFit.py
xPlotUtil/Source/ReadSpecFile.py
xPlotUtil/Source/__init__.py
xPlotUtil/Source/voltage_dialog.py
xPlotUtil-1.1.6.data/scripts/xPlotUtil
xPlotUtil-1.1.6.data/scripts/xPlotUtil.bat
xPlotUtil-1.1.6.dist-info/DESCRIPTION.rst
xPlotUtil-1.1.6.dist-info/METADATA
xPlotUtil-1.1.6.dist-info/RECORD
xPlotUtil-1.1.6.dist-info/WHEEL
xPlotUtil-1.1.6.dist-info/metadata.json
xPlotUtil-1.1.6.dist-info/top_level.txt
