Metadata-Version: 2.0
Name: xPlotUtil
Version: 1.1.6
Summary: The program provides a GUI for the user to graph the data in different forms, normalize and fit it.
Home-page: https://github.com/AdvancedPhotonSource/xPlotUtil
Author: Phaulo C. Escalante
Author-email: escalante.phaulo@outlook.com
License: See LICENSE File
Platform: any
Requires-Dist: future
Requires-Dist: lmfit
Requires-Dist: matplotlib
Requires-Dist: numpy
Requires-Dist: spec2nexus
